<?xml version="1.0" encoding="UTF-8"?><DataModel ModuleName="mempoolstats" Version="1.0" schemaVersion="3.0">

	 <InstallPath>on_director.mempoolstats</InstallPath>
	<DataModelNode>
                 <InstallPath>mempoolname</InstallPath>
                 <Name>mempoolname</Name>
                 <FriendlyName>mempoolname</FriendlyName>
                 <NodeID>299</NodeID>
                 <Description>mempoolname</Description>
                 <SaveDirName>CM_CONFIG_DIR</SaveDirName>
                 <StorageFileName>NULL</StorageFileName>
                 <NodeAttributes>
                                <NodeType>CM_DMNODE_TYPE_SCALAR_VAR</NodeType>
                                <Visible>FALSE</Visible>
                                <IsKey>TRUE</IsKey>
                                <Mandatory>TRUE</Mandatory>
                                <OrderedTable>FALSE</OrderedTable>
                                <PriorityNode>FALSE</PriorityNode>
                                <NotifyChange>TRUE</NotifyChange>
                                <NotifyType>CM_NOT_CHANGEABLE_BY_ACS</NotifyType>
                                <RebootOnChange>FALSE</RebootOnChange>
                                <StickyToParent>FALSE</StickyToParent>
                                <SaveInParentDir>TRUE</SaveInParentDir>
                                <NonConfigLeafNode>TRUE</NonConfigLeafNode>
                                <AccessControl>CM_ACCESS_ALL</AccessControl>
                                <GroupedScalar>FALSE</GroupedScalar>
                                <GlobalTrans>FALSE</GlobalTrans>
                                <UseParentTrans>FALSE</UseParentTrans>
                 </NodeAttributes>
                 <DataAttributes>
                                <DataType>CM_DATA_TYPE_STRING</DataType>
                                <Type>CM_DATA_ATTRIB_STR_RANGE</Type>
                                <DataAttrib>
                                         <MinLength>0</MinLength>
                                         <MaxLength>100</MaxLength>
                                </DataAttrib>
                                <DefaultValue>
                                         <DefaultString/>
                                </DefaultValue>
                 </DataAttributes>
        </DataModelNode>
	 <DataModelNode>
         <InstallPath>freeblockscount</InstallPath>
         <Name>freeblockscount</Name>
         <FriendlyName>freeblockscount</FriendlyName>
         <NodeID>300</NodeID>
         <Description>freeblockscount</Description>
         <SaveDirName>CM_CONFIG_DIR</SaveDirName>
         <StorageFileName>NULL</StorageFileName>
         <NodeAttributes>
             <NodeType>CM_DMNODE_TYPE_SCALAR_VAR</NodeType>
             <Visible>FALSE</Visible>
             <IsKey>FALSE</IsKey>
             <Mandatory>FALSE</Mandatory>
             <OrderedTable>FALSE</OrderedTable>
             <PriorityNode>FALSE</PriorityNode>
             <NotifyChange>TRUE</NotifyChange> 
             <NotifyType>CM_NOT_CHANGEABLE_BY_ACS</NotifyType>
             <RebootOnChange>FALSE</RebootOnChange>
             <StickyToParent>FALSE</StickyToParent>
             <SaveInParentDir>FALSE</SaveInParentDir>
             <NonConfigLeafNode>FALSE</NonConfigLeafNode>
             <AccessControl>CM_ACCESS_ALL</AccessControl>
             <GroupedScalar>FALSE</GroupedScalar>
             <GlobalTrans>FALSE</GlobalTrans>
             <UseParentTrans>FALSE</UseParentTrans>
         </NodeAttributes>
         <DataAttributes>
             <DataType>CM_DATA_TYPE_UINT</DataType>
		 <Type>CM_DATA_ATTRIB_NONE</Type>
	      <DataAttrib/>
         </DataAttributes>
         </DataModelNode>
	 <DataModelNode>
         <InstallPath>allocatedblockscount</InstallPath>
         <Name>allocatedblockscount</Name>
         <FriendlyName>allocatedblockscount</FriendlyName>
         <NodeID>301</NodeID>
         <Description>allocatedblockscount</Description>
         <SaveDirName>CM_CONFIG_DIR</SaveDirName>
         <StorageFileName>NULL</StorageFileName>
         <NodeAttributes>
             <NodeType>CM_DMNODE_TYPE_SCALAR_VAR</NodeType>
             <Visible>FALSE</Visible>
             <IsKey>FALSE</IsKey>
             <Mandatory>FALSE</Mandatory>
             <OrderedTable>FALSE</OrderedTable>
             <PriorityNode>FALSE</PriorityNode>
             <NotifyChange>TRUE</NotifyChange> 
             <NotifyType>CM_NOT_CHANGEABLE_BY_ACS</NotifyType>
             <RebootOnChange>FALSE</RebootOnChange>
             <StickyToParent>FALSE</StickyToParent>
             <SaveInParentDir>FALSE</SaveInParentDir>
             <NonConfigLeafNode>FALSE</NonConfigLeafNode>
             <AccessControl>CM_ACCESS_ALL</AccessControl>
             <GroupedScalar>FALSE</GroupedScalar>
             <GlobalTrans>FALSE</GlobalTrans>
             <UseParentTrans>FALSE</UseParentTrans>
         </NodeAttributes>
         <DataAttributes>
             <DataType>CM_DATA_TYPE_UINT</DataType>
		 <Type>CM_DATA_ATTRIB_NONE</Type>
	      <DataAttrib/>
         </DataAttributes>
         </DataModelNode>
	 <DataModelNode>
         <InstallPath>releasedblockscount</InstallPath>
         <Name>releasedblockscount</Name>
         <FriendlyName>releasedblockscount</FriendlyName>
         <NodeID>302</NodeID>
         <Description>releasedblockscount</Description>
         <SaveDirName>CM_CONFIG_DIR</SaveDirName>
         <StorageFileName>NULL</StorageFileName>
         <NodeAttributes>
             <NodeType>CM_DMNODE_TYPE_SCALAR_VAR</NodeType>
             <Visible>FALSE</Visible>
             <IsKey>FALSE</IsKey>
             <Mandatory>FALSE</Mandatory>
             <OrderedTable>FALSE</OrderedTable>
             <PriorityNode>FALSE</PriorityNode>
             <NotifyChange>TRUE</NotifyChange> 
             <NotifyType>CM_NOT_CHANGEABLE_BY_ACS</NotifyType>
             <RebootOnChange>FALSE</RebootOnChange>
             <StickyToParent>FALSE</StickyToParent>
             <SaveInParentDir>FALSE</SaveInParentDir>
             <NonConfigLeafNode>FALSE</NonConfigLeafNode>
             <AccessControl>CM_ACCESS_ALL</AccessControl>
             <GroupedScalar>FALSE</GroupedScalar>
             <GlobalTrans>FALSE</GlobalTrans>
             <UseParentTrans>FALSE</UseParentTrans>
         </NodeAttributes>
         <DataAttributes>
             <DataType>CM_DATA_TYPE_UINT</DataType>
		 <Type>CM_DATA_ATTRIB_NONE</Type>
	      <DataAttrib/>
         </DataAttributes>
         </DataModelNode>
	 <DataModelNode>
         <InstallPath>allocationfailblocks_count</InstallPath>
         <Name>allocationfailblocks_count</Name>
         <FriendlyName>allocationfailblocks_count</FriendlyName>
         <NodeID>303</NodeID>
         <Description>allocationfailblocks_count</Description>
         <SaveDirName>CM_CONFIG_DIR</SaveDirName>
         <StorageFileName>NULL</StorageFileName>
         <NodeAttributes>
             <NodeType>CM_DMNODE_TYPE_SCALAR_VAR</NodeType>
             <Visible>FALSE</Visible>
             <IsKey>FALSE</IsKey>
             <Mandatory>FALSE</Mandatory>
             <OrderedTable>FALSE</OrderedTable>
             <PriorityNode>FALSE</PriorityNode>
             <NotifyChange>TRUE</NotifyChange> 
             <NotifyType>CM_NOT_CHANGEABLE_BY_ACS</NotifyType>
             <RebootOnChange>FALSE</RebootOnChange>
             <StickyToParent>FALSE</StickyToParent>
             <SaveInParentDir>FALSE</SaveInParentDir>
             <NonConfigLeafNode>FALSE</NonConfigLeafNode>
             <AccessControl>CM_ACCESS_ALL</AccessControl>
             <GroupedScalar>FALSE</GroupedScalar>
             <GlobalTrans>FALSE</GlobalTrans>
             <UseParentTrans>FALSE</UseParentTrans>
         </NodeAttributes>
         <DataAttributes>
             <DataType>CM_DATA_TYPE_UINT</DataType>
		 <Type>CM_DATA_ATTRIB_NONE</Type>
	      <DataAttrib/>
         </DataAttributes>
         </DataModelNode>
	 <DataModelNode>
         <InstallPath>releasedfailblockscount</InstallPath>
         <Name>releasedfailblockscount</Name>
         <FriendlyName>releasedfailblockscount</FriendlyName>
         <NodeID>304</NodeID>
         <Description>releasedfailblockscount</Description>
         <SaveDirName>CM_CONFIG_DIR</SaveDirName>
         <StorageFileName>NULL</StorageFileName>
         <NodeAttributes>
             <NodeType>CM_DMNODE_TYPE_SCALAR_VAR</NodeType>
             <Visible>FALSE</Visible>
             <IsKey>FALSE</IsKey>
             <Mandatory>FALSE</Mandatory>
             <OrderedTable>FALSE</OrderedTable>
             <PriorityNode>FALSE</PriorityNode>
             <NotifyChange>TRUE</NotifyChange> 
             <NotifyType>CM_NOT_CHANGEABLE_BY_ACS</NotifyType>
             <RebootOnChange>FALSE</RebootOnChange>
             <StickyToParent>FALSE</StickyToParent>
             <SaveInParentDir>FALSE</SaveInParentDir>
             <NonConfigLeafNode>FALSE</NonConfigLeafNode>
             <AccessControl>CM_ACCESS_ALL</AccessControl>
             <GroupedScalar>FALSE</GroupedScalar>
             <GlobalTrans>FALSE</GlobalTrans>
             <UseParentTrans>FALSE</UseParentTrans>
         </NodeAttributes>
         <DataAttributes>
             <DataType>CM_DATA_TYPE_UINT</DataType>
		 <Type>CM_DATA_ATTRIB_NONE</Type>
	      <DataAttrib/>
         </DataAttributes>
         </DataModelNode>
	 <DataModelNode>
         <InstallPath>heapfreeblockscount</InstallPath>
         <Name>heapfreeblockscount</Name>
         <FriendlyName>heapfreeblockscount</FriendlyName>
         <NodeID>305</NodeID>
         <Description>heapfreeblockscount</Description>
         <SaveDirName>CM_CONFIG_DIR</SaveDirName>
         <StorageFileName>NULL</StorageFileName>
         <NodeAttributes>
             <NodeType>CM_DMNODE_TYPE_SCALAR_VAR</NodeType>
             <Visible>FALSE</Visible>
             <IsKey>FALSE</IsKey>
             <Mandatory>FALSE</Mandatory>
             <OrderedTable>FALSE</OrderedTable>
             <PriorityNode>FALSE</PriorityNode>
             <NotifyChange>TRUE</NotifyChange> 
             <NotifyType>CM_NOT_CHANGEABLE_BY_ACS</NotifyType>
             <RebootOnChange>FALSE</RebootOnChange>
             <StickyToParent>FALSE</StickyToParent>
             <SaveInParentDir>FALSE</SaveInParentDir>
             <NonConfigLeafNode>FALSE</NonConfigLeafNode>
             <AccessControl>CM_ACCESS_ALL</AccessControl>
             <GroupedScalar>FALSE</GroupedScalar>
             <GlobalTrans>FALSE</GlobalTrans>
             <UseParentTrans>FALSE</UseParentTrans>
         </NodeAttributes>
         <DataAttributes>
             <DataType>CM_DATA_TYPE_UINT</DataType>
		 <Type>CM_DATA_ATTRIB_NONE</Type>
	      <DataAttrib/>
         </DataAttributes>
         </DataModelNode>
	 <DataModelNode>
         <InstallPath>heapallocatedblockscount</InstallPath>
         <Name>heapallocatedblockscount</Name>
         <FriendlyName>heapallocatedblockscount</FriendlyName>
         <NodeID>306</NodeID>
         <Description>heapallocatedblockscount</Description>
         <SaveDirName>CM_CONFIG_DIR</SaveDirName>
         <StorageFileName>NULL</StorageFileName>
         <NodeAttributes>
             <NodeType>CM_DMNODE_TYPE_SCALAR_VAR</NodeType>
             <Visible>FALSE</Visible>
             <IsKey>FALSE</IsKey>
             <Mandatory>FALSE</Mandatory>
             <OrderedTable>FALSE</OrderedTable>
             <PriorityNode>FALSE</PriorityNode>
             <NotifyChange>TRUE</NotifyChange> 
             <NotifyType>CM_NOT_CHANGEABLE_BY_ACS</NotifyType>
             <RebootOnChange>FALSE</RebootOnChange>
             <StickyToParent>FALSE</StickyToParent>
             <SaveInParentDir>FALSE</SaveInParentDir>
             <NonConfigLeafNode>FALSE</NonConfigLeafNode>
             <AccessControl>CM_ACCESS_ALL</AccessControl>
             <GroupedScalar>FALSE</GroupedScalar>
             <GlobalTrans>FALSE</GlobalTrans>
             <UseParentTrans>FALSE</UseParentTrans>
         </NodeAttributes>
         <DataAttributes>
             <DataType>CM_DATA_TYPE_UINT</DataType>
		 <Type>CM_DATA_ATTRIB_NONE</Type>
	      <DataAttrib/>
         </DataAttributes>
         </DataModelNode>
	 <DataModelNode>
         <InstallPath>heapreleasedblockscount</InstallPath>
         <Name>heapreleasedblockscount</Name>
         <FriendlyName>heapreleasedblockscount</FriendlyName>
         <NodeID>307</NodeID>
         <Description>heapreleasedblockscount</Description>
         <SaveDirName>CM_CONFIG_DIR</SaveDirName>
         <StorageFileName>NULL</StorageFileName>
         <NodeAttributes>
             <NodeType>CM_DMNODE_TYPE_SCALAR_VAR</NodeType>
             <Visible>FALSE</Visible>
             <IsKey>FALSE</IsKey>
             <Mandatory>FALSE</Mandatory>
             <OrderedTable>FALSE</OrderedTable>
             <PriorityNode>FALSE</PriorityNode>
             <NotifyChange>TRUE</NotifyChange> 
             <NotifyType>CM_NOT_CHANGEABLE_BY_ACS</NotifyType>
             <RebootOnChange>FALSE</RebootOnChange>
             <StickyToParent>FALSE</StickyToParent>
             <SaveInParentDir>FALSE</SaveInParentDir>
             <NonConfigLeafNode>FALSE</NonConfigLeafNode>
             <AccessControl>CM_ACCESS_ALL</AccessControl>
             <GroupedScalar>FALSE</GroupedScalar>
             <GlobalTrans>FALSE</GlobalTrans>
             <UseParentTrans>FALSE</UseParentTrans>
         </NodeAttributes>
         <DataAttributes>
             <DataType>CM_DATA_TYPE_UINT</DataType>
		 <Type>CM_DATA_ATTRIB_NONE</Type>
	      <DataAttrib/>
         </DataAttributes>
         </DataModelNode>
	 <DataModelNode>
         <InstallPath>heapallocationfailblockscount</InstallPath>
         <Name>heapallocationfailblockscount</Name>
         <FriendlyName>heapallocationfailblockscount</FriendlyName>
         <NodeID>308</NodeID>
         <Description>heapallocationfailblockscount</Description>
         <SaveDirName>CM_CONFIG_DIR</SaveDirName>
         <StorageFileName>NULL</StorageFileName>
         <NodeAttributes>
             <NodeType>CM_DMNODE_TYPE_SCALAR_VAR</NodeType>
             <Visible>FALSE</Visible>
             <IsKey>FALSE</IsKey>
             <Mandatory>FALSE</Mandatory>
             <OrderedTable>FALSE</OrderedTable>
             <PriorityNode>FALSE</PriorityNode>
             <NotifyChange>TRUE</NotifyChange> 
             <NotifyType>CM_NOT_CHANGEABLE_BY_ACS</NotifyType>
             <RebootOnChange>FALSE</RebootOnChange>
             <StickyToParent>FALSE</StickyToParent>
             <SaveInParentDir>FALSE</SaveInParentDir>
             <NonConfigLeafNode>FALSE</NonConfigLeafNode>
             <AccessControl>CM_ACCESS_ALL</AccessControl>
             <GroupedScalar>FALSE</GroupedScalar>
             <GlobalTrans>FALSE</GlobalTrans>
             <UseParentTrans>FALSE</UseParentTrans>
         </NodeAttributes>
         <DataAttributes>
             <DataType>CM_DATA_TYPE_UINT</DataType>
		 <Type>CM_DATA_ATTRIB_NONE</Type>
	      <DataAttrib/>
         </DataAttributes>
         </DataModelNode>
	 <DataModelNode>
         <InstallPath>heapallowedblockscount</InstallPath>
         <Name>heapallowedblockscount</Name>
         <FriendlyName>heapallowedblockscount</FriendlyName>
         <NodeID>309</NodeID>
         <Description>heapallowedblockscount</Description>
         <SaveDirName>CM_CONFIG_DIR</SaveDirName>
         <StorageFileName>NULL</StorageFileName>
         <NodeAttributes>
             <NodeType>CM_DMNODE_TYPE_SCALAR_VAR</NodeType>
             <Visible>FALSE</Visible>
             <IsKey>FALSE</IsKey>
             <Mandatory>FALSE</Mandatory>
             <OrderedTable>FALSE</OrderedTable>
             <PriorityNode>FALSE</PriorityNode>
             <NotifyChange>TRUE</NotifyChange> 
             <NotifyType>CM_NOT_CHANGEABLE_BY_ACS</NotifyType>
             <RebootOnChange>FALSE</RebootOnChange>
             <StickyToParent>FALSE</StickyToParent>
             <SaveInParentDir>FALSE</SaveInParentDir>
             <NonConfigLeafNode>FALSE</NonConfigLeafNode>
             <AccessControl>CM_ACCESS_ALL</AccessControl>
             <GroupedScalar>FALSE</GroupedScalar>
             <GlobalTrans>FALSE</GlobalTrans>
             <UseParentTrans>FALSE</UseParentTrans>
         </NodeAttributes>
         <DataAttributes>
             <DataType>CM_DATA_TYPE_UINT</DataType>
		 <Type>CM_DATA_ATTRIB_NONE</Type>
	      <DataAttrib/>
         </DataAttributes>
         </DataModelNode>
	 <DataModelNode>
         <InstallPath>staticblocks</InstallPath>
         <Name>staticblocks</Name>
         <FriendlyName>staticblocks</FriendlyName>
         <NodeID>310</NodeID>
         <Description>staticblocks</Description>
         <SaveDirName>CM_CONFIG_DIR</SaveDirName>
         <StorageFileName>NULL</StorageFileName>
         <NodeAttributes>
             <NodeType>CM_DMNODE_TYPE_SCALAR_VAR</NodeType>
             <Visible>FALSE</Visible>
             <IsKey>FALSE</IsKey>
             <Mandatory>FALSE</Mandatory>
             <OrderedTable>FALSE</OrderedTable>
             <PriorityNode>FALSE</PriorityNode>
             <NotifyChange>TRUE</NotifyChange> 
             <NotifyType>CM_NOT_CHANGEABLE_BY_ACS</NotifyType>
             <RebootOnChange>FALSE</RebootOnChange>
             <StickyToParent>FALSE</StickyToParent>
             <SaveInParentDir>FALSE</SaveInParentDir>
             <NonConfigLeafNode>FALSE</NonConfigLeafNode>
             <AccessControl>CM_ACCESS_ALL</AccessControl>
             <GroupedScalar>FALSE</GroupedScalar>
             <GlobalTrans>FALSE</GlobalTrans>
             <UseParentTrans>FALSE</UseParentTrans>
         </NodeAttributes>
         <DataAttributes>
             <DataType>CM_DATA_TYPE_UINT</DataType>
		 <Type>CM_DATA_ATTRIB_NONE</Type>
	      <DataAttrib/>
         </DataAttributes>
         </DataModelNode>
	 <DataModelNode>
         <InstallPath>totalblockscount</InstallPath>
         <Name>totalblockscount</Name>
         <FriendlyName>totalblockscount</FriendlyName>
         <NodeID>311</NodeID>
         <Description>totalblockscount</Description>
         <SaveDirName>CM_CONFIG_DIR</SaveDirName>
         <StorageFileName>NULL</StorageFileName>
         <NodeAttributes>
             <NodeType>CM_DMNODE_TYPE_SCALAR_VAR</NodeType>
             <Visible>FALSE</Visible>
             <IsKey>FALSE</IsKey>
             <Mandatory>FALSE</Mandatory>
             <OrderedTable>FALSE</OrderedTable>
             <PriorityNode>FALSE</PriorityNode>
             <NotifyChange>TRUE</NotifyChange> 
             <NotifyType>CM_NOT_CHANGEABLE_BY_ACS</NotifyType>
             <RebootOnChange>FALSE</RebootOnChange>
             <StickyToParent>FALSE</StickyToParent>
             <SaveInParentDir>FALSE</SaveInParentDir>
             <NonConfigLeafNode>FALSE</NonConfigLeafNode>
             <AccessControl>CM_ACCESS_ALL</AccessControl>
             <GroupedScalar>FALSE</GroupedScalar>
             <GlobalTrans>FALSE</GlobalTrans>
             <UseParentTrans>FALSE</UseParentTrans>
         </NodeAttributes>
         <DataAttributes>
             <DataType>CM_DATA_TYPE_UINT</DataType>
		 <Type>CM_DATA_ATTRIB_NONE</Type>
	      <DataAttrib/>
         </DataAttributes>
         </DataModelNode>
	 <DataModelNode>
         <InstallPath>blocksize</InstallPath>
         <Name>blocksize</Name>
         <FriendlyName>blocksize</FriendlyName>
         <NodeID>312</NodeID>
         <Description>blocksize</Description>
         <SaveDirName>CM_CONFIG_DIR</SaveDirName>
         <StorageFileName>NULL</StorageFileName>
         <NodeAttributes>
             <NodeType>CM_DMNODE_TYPE_SCALAR_VAR</NodeType>
             <Visible>FALSE</Visible>
             <IsKey>FALSE</IsKey>
             <Mandatory>FALSE</Mandatory>
             <OrderedTable>FALSE</OrderedTable>
             <PriorityNode>FALSE</PriorityNode>
             <NotifyChange>TRUE</NotifyChange> 
             <NotifyType>CM_NOT_CHANGEABLE_BY_ACS</NotifyType>
             <RebootOnChange>FALSE</RebootOnChange>
             <StickyToParent>FALSE</StickyToParent>
             <SaveInParentDir>FALSE</SaveInParentDir>
             <NonConfigLeafNode>FALSE</NonConfigLeafNode>
             <AccessControl>CM_ACCESS_ALL</AccessControl>
             <GroupedScalar>FALSE</GroupedScalar>
             <GlobalTrans>FALSE</GlobalTrans>
             <UseParentTrans>FALSE</UseParentTrans>
         </NodeAttributes>
         <DataAttributes>
             <DataType>CM_DATA_TYPE_UINT</DataType>
		 <Type>CM_DATA_ATTRIB_NONE</Type>
	      <DataAttrib/>
         </DataAttributes>
         </DataModelNode>
	 <DataModelNode>
         <InstallPath>staticallocatedblockscount</InstallPath>
         <Name>staticallocatedblockscount</Name>
         <FriendlyName>staticallocatedblockscount</FriendlyName>
         <NodeID>313</NodeID>
         <Description>staticallocatedblockscount</Description>
         <SaveDirName>CM_CONFIG_DIR</SaveDirName>
         <StorageFileName>NULL</StorageFileName>
         <NodeAttributes>
             <NodeType>CM_DMNODE_TYPE_SCALAR_VAR</NodeType>
             <Visible>FALSE</Visible>
             <IsKey>FALSE</IsKey>
             <Mandatory>FALSE</Mandatory>
             <OrderedTable>FALSE</OrderedTable>
             <PriorityNode>FALSE</PriorityNode>
             <NotifyChange>TRUE</NotifyChange> 
             <NotifyType>CM_NOT_CHANGEABLE_BY_ACS</NotifyType>
             <RebootOnChange>FALSE</RebootOnChange>
             <StickyToParent>FALSE</StickyToParent>
             <SaveInParentDir>FALSE</SaveInParentDir>
             <NonConfigLeafNode>FALSE</NonConfigLeafNode>
             <AccessControl>CM_ACCESS_ALL</AccessControl>
             <GroupedScalar>FALSE</GroupedScalar>
             <GlobalTrans>FALSE</GlobalTrans>
             <UseParentTrans>FALSE</UseParentTrans>
         </NodeAttributes>
         <DataAttributes>
             <DataType>CM_DATA_TYPE_UINT</DataType>
		 <Type>CM_DATA_ATTRIB_NONE</Type>
	      <DataAttrib/>
         </DataAttributes>
         </DataModelNode>
	 <DataModelNode>
         <InstallPath>threshold_max</InstallPath>
         <Name>threshold_max</Name>
         <FriendlyName>threshold_max</FriendlyName>
         <NodeID>314</NodeID>
         <Description>threshold_max</Description>
         <SaveDirName>CM_CONFIG_DIR</SaveDirName>
         <StorageFileName>NULL</StorageFileName>
         <NodeAttributes>
             <NodeType>CM_DMNODE_TYPE_SCALAR_VAR</NodeType>
             <Visible>FALSE</Visible>
             <IsKey>FALSE</IsKey>
             <Mandatory>FALSE</Mandatory>
             <OrderedTable>FALSE</OrderedTable>
             <PriorityNode>FALSE</PriorityNode>
             <NotifyChange>TRUE</NotifyChange> 
             <NotifyType>CM_NOT_CHANGEABLE_BY_ACS</NotifyType>
             <RebootOnChange>FALSE</RebootOnChange>
             <StickyToParent>FALSE</StickyToParent>
             <SaveInParentDir>FALSE</SaveInParentDir>
             <NonConfigLeafNode>FALSE</NonConfigLeafNode>
             <AccessControl>CM_ACCESS_ALL</AccessControl>
             <GroupedScalar>FALSE</GroupedScalar>
             <GlobalTrans>FALSE</GlobalTrans>
             <UseParentTrans>FALSE</UseParentTrans>
         </NodeAttributes>
         <DataAttributes>
             <DataType>CM_DATA_TYPE_UINT</DataType>
		 <Type>CM_DATA_ATTRIB_NONE</Type>
	      <DataAttrib/>
         </DataAttributes>
         </DataModelNode>
	 <DataModelNode>
         <InstallPath>thresholdmin</InstallPath>
         <Name>thresholdmin</Name>
         <FriendlyName>thresholdmin</FriendlyName>
         <NodeID>315</NodeID>
         <Description>thresholdmin</Description>
         <SaveDirName>CM_CONFIG_DIR</SaveDirName>
         <StorageFileName>NULL</StorageFileName>
         <NodeAttributes>
             <NodeType>CM_DMNODE_TYPE_SCALAR_VAR</NodeType>
             <Visible>FALSE</Visible>
             <IsKey>FALSE</IsKey>
             <Mandatory>FALSE</Mandatory>
             <OrderedTable>FALSE</OrderedTable>
             <PriorityNode>FALSE</PriorityNode>
             <NotifyChange>TRUE</NotifyChange> 
             <NotifyType>CM_NOT_CHANGEABLE_BY_ACS</NotifyType>
             <RebootOnChange>FALSE</RebootOnChange>
             <StickyToParent>FALSE</StickyToParent>
             <SaveInParentDir>FALSE</SaveInParentDir>
             <NonConfigLeafNode>FALSE</NonConfigLeafNode>
             <AccessControl>CM_ACCESS_ALL</AccessControl>
             <GroupedScalar>FALSE</GroupedScalar>
             <GlobalTrans>FALSE</GlobalTrans>
             <UseParentTrans>FALSE</UseParentTrans>
         </NodeAttributes>
         <DataAttributes>
             <DataType>CM_DATA_TYPE_UINT</DataType>
		 <Type>CM_DATA_ATTRIB_NONE</Type>
	      <DataAttrib/>
         </DataAttributes>
         </DataModelNode>
	 <DataModelNode>
         <InstallPath>replenishcount</InstallPath>
         <Name>replenishcount</Name>
         <FriendlyName>replenishcount</FriendlyName>
         <NodeID>316</NodeID>
         <Description>replenishcount</Description>
         <SaveDirName>CM_CONFIG_DIR</SaveDirName>
         <StorageFileName>NULL</StorageFileName>
         <NodeAttributes>
             <NodeType>CM_DMNODE_TYPE_SCALAR_VAR</NodeType>
             <Visible>FALSE</Visible>
             <IsKey>FALSE</IsKey>
             <Mandatory>FALSE</Mandatory>
             <OrderedTable>FALSE</OrderedTable>
             <PriorityNode>FALSE</PriorityNode>
             <NotifyChange>TRUE</NotifyChange> 
             <NotifyType>CM_NOT_CHANGEABLE_BY_ACS</NotifyType>
             <RebootOnChange>FALSE</RebootOnChange>
             <StickyToParent>FALSE</StickyToParent>
             <SaveInParentDir>FALSE</SaveInParentDir>
             <NonConfigLeafNode>FALSE</NonConfigLeafNode>
             <AccessControl>CM_ACCESS_ALL</AccessControl>
             <GroupedScalar>FALSE</GroupedScalar>
             <GlobalTrans>FALSE</GlobalTrans>
             <UseParentTrans>FALSE</UseParentTrans>
         </NodeAttributes>
         <DataAttributes>
             <DataType>CM_DATA_TYPE_UINT</DataType>
		 <Type>CM_DATA_ATTRIB_NONE</Type>
	      <DataAttrib/>
         </DataAttributes>
         </DataModelNode>
</DataModel>
